{"type":"cmds","vnumber":100,"ctx":{"name":"group","intro_on":true,"intro":"","hex_on":false,"loop_on":true,"loop_ms":100,"loop_count":1,"cmd_hex":"","is_group":true,"down":true,"subCmds":[{"name":"x","intro_on":true,"intro":"","hex_on":true,"loop_on":true,"loop_ms":100,"loop_count":1,"cmd_hex":"55 AA 00 11 %%","is_group":false,"down":false,"subCmds":[]},{"name":"y","intro_on":true,"intro":"","hex_on":true,"loop_on":true,"loop_ms":100,"loop_count":1,"cmd_hex":"55 AA 00 12 %%","is_group":false,"down":false,"subCmds":[]},{"name":"move","intro_on":true,"intro":"","hex_on":true,"loop_on":true,"loop_ms":10,"loop_count":1,"cmd_hex":"5A A5 00 00 %% %%","is_group":false,"down":false,"subCmds":[]},{"name":"pos","intro_on":true,"intro":"","hex_on":true,"loop_on":true,"loop_ms":10,"loop_count":1,"cmd_hex":"5A A5 00 01 %% %%","is_group":false,"down":false,"subCmds":[]},{"name":"lock","intro_on":true,"intro":"","hex_on":true,"loop_on":true,"loop_ms":10,"loop_count":1,"cmd_hex":"5A A5 00 02 %% ","is_group":false,"down":false,"subCmds":[]},{"name":"config","intro_on":true,"intro":"","hex_on":true,"loop_on":true,"loop_ms":100,"loop_count":1,"cmd_hex":"5A A5 00 03 %%","is_group":false,"down":false,"subCmds":[]},{"name":"val","intro_on":true,"intro":"","hex_on":true,"loop_on":true,"loop_ms":100,"loop_count":1,"cmd_hex":"5A A5 00 04 %%","is_group":false,"down":false,"subCmds":[]},{"name":"yawC","intro_on":true,"intro":"","hex_on":true,"loop_on":true,"loop_ms":10,"loop_count":1,"cmd_hex":"5A A5 00 05 %%","is_group":false,"down":false,"subCmds":[]},{"name":"deep","intro_on":true,"intro":"","hex_on":true,"loop_on":true,"loop_ms":20,"loop_count":1,"cmd_hex":"5A A5 00 06 %%","is_group":false,"down":false,"subCmds":[]}]}}